WifiScanner/Scanner.py
WifiScanner/__init__.py
WifiScanner-0.0.2.dist-info/METADATA
WifiScanner-0.0.2.dist-info/WHEEL
WifiScanner-0.0.2.dist-info/top_level.txt
WifiScanner-0.0.2.dist-info/RECORD
